podaac/subsetter/__init__.py
podaac/subsetter/datatree_subset.py
podaac/subsetter/dimension_cleanup.py
podaac/subsetter/run_subsetter.py
podaac/subsetter/subset.py
podaac/subsetter/subset_harmony.py
podaac/subsetter/tree_time_converting.py
podaac/subsetter/utils/coordinate_utils.py
podaac/subsetter/utils/file_utils.py
podaac/subsetter/utils/mask_utils.py
podaac/subsetter/utils/metadata_utils.py
podaac/subsetter/utils/spatial_utils.py
podaac/subsetter/utils/time_utils.py
podaac/subsetter/utils/variables_utils.py
l2ss_py-3.2.0.dist-info/LICENSE
l2ss_py-3.2.0.dist-info/METADATA
l2ss_py-3.2.0.dist-info/WHEEL
l2ss_py-3.2.0.dist-info/entry_points.txt
l2ss_py-3.2.0.dist-info/RECORD
