Metadata-Version: 2.3
Name: l2ss-py
Version: 3.2.0
Summary: L2 Subsetter Service
License: Apache-2.0
Author: podaac-tva
Author-email: podaac-tva@jpl.nasa.gov
Requires-Python: >=3.12,<4.0
Classifier: License :: OSI Approved :: Apache Software License
Classifier: Programming Language :: Python :: 3
Classifier: Programming Language :: Python :: 3.12
Classifier: Programming Language :: Python :: 3.13
Classifier: Topic :: Software Development :: Libraries :: Python Modules
Provides-Extra: harmony
Requires-Dist: Shapely (>=2.0.6,<3.0.0)
Requires-Dist: cf-xarray
Requires-Dist: geopandas (>=1.0.1,<2.0.0)
Requires-Dist: h5py (>=3.6.0,<4.0.0)
Requires-Dist: harmony-service-lib (>=2.0.0,<3.0.0) ; extra == "harmony"
Requires-Dist: importlib-metadata (>=8.2.0,<9.0.0)
Requires-Dist: julian (>=0.14,<0.15)
Requires-Dist: netCDF4 (>=1.5,<2.0)
Requires-Dist: numpy (>=2.2.4,<3.0.0)
Requires-Dist: poetry (>=2.1.3,<3.0.0)
Requires-Dist: pystac (>=1.10.1,<2.0.0) ; extra == "harmony"
Requires-Dist: xarray[parallel] (<=2025.1.0)
Project-URL: Repository, https://github.com/podaac/l2ss-py
